py_troya_connect/__init__.py
py_troya_connect/terminal.py
py_troya_connect-0.1.3152.dist-info/LICENSE
py_troya_connect-0.1.3152.dist-info/METADATA
py_troya_connect-0.1.3152.dist-info/WHEEL
py_troya_connect-0.1.3152.dist-info/entry_points.txt
py_troya_connect-0.1.3152.dist-info/top_level.txt
py_troya_connect-0.1.3152.dist-info/RECORD
